package com.google.zxing.oned;

import java.util.ArrayList;
import java.util.List;

final class EANManufacturerOrgSupport
{
  private final List<String> countryIdentifiers = new ArrayList();
  private final List<int[]> ranges = new ArrayList();
  
  private void add(int[] paramArrayOfInt, String paramString)
  {
    this.ranges.add(paramArrayOfInt);
    this.countryIdentifiers.add(paramString);
  }
  
  /* Error */
  private void initIfNeeded()
  {
    // Byte code:
    //   0: aload_0
    //   1: monitorenter
    //   2: aload_0
    //   3: getfield 18	com/google/zxing/oned/EANManufacturerOrgSupport:ranges	Ljava/util/List;
    //   6: invokeinterface 33 1 0
    //   11: istore_1
    //   12: iload_1
    //   13: ifne +6 -> 19
    //   16: aload_0
    //   17: monitorexit
    //   18: return
    //   19: iconst_2
    //   20: newarray <illegal type>
    //   22: astore_2
    //   23: aload_2
    //   24: iconst_1
    //   25: bipush 19
    //   27: iastore
    //   28: aload_0
    //   29: aload_2
    //   30: ldc 35
    //   32: invokespecial 37	com/google/zxing/oned/EANManufacturerOrgSupport:add	([ILjava/lang/String;)V
    //   35: aload_0
    //   36: iconst_2
    //   37: newarray <illegal type>
    //   39: dup
    //   40: iconst_0
    //   41: bipush 30
    //   43: iastore
    //   44: dup
    //   45: iconst_1
    //   46: bipush 39
    //   48: iastore
    //   49: ldc 39
    //   51: invokespecial 37	com/google/zxing/oned/EANManufacturerOrgSupport:add	([ILjava/lang/String;)V
    //   54: aload_0
    //   55: iconst_2
    //   56: newarray <illegal type>
    //   58: dup
    //   59: iconst_0
    //   60: bipush 60
    //   62: iastore
    //   63: dup
    //   64: iconst_1
    //   65: sipush 139
    //   68: iastore
    //   69: ldc 35
    //   71: invokespecial 37	com/google/zxing/oned/EANManufacturerOrgSupport:add	([ILjava/lang/String;)V
    //   74: aload_0
    //   75: iconst_2
    //   76: newarray <illegal type>
    //   78: dup
    //   79: iconst_0
    //   80: sipush 300
    //   83: iastore
    //   84: dup
    //   85: iconst_1
    //   86: sipush 379
    //   89: iastore
    //   90: ldc 41
    //   92: invokespecial 37	com/google/zxing/oned/EANManufacturerOrgSupport:add	([ILjava/lang/String;)V
    //   95: aload_0
    //   96: iconst_1
    //   97: newarray <illegal type>
    //   99: dup
    //   100: iconst_0
    //   101: sipush 380
    //   104: iastore
    //   105: ldc 43
    //   107: invokespecial 37	com/google/zxing/oned/EANManufacturerOrgSupport:add	([ILjava/lang/String;)V
    //   110: aload_0
    //   111: iconst_1
    //   112: newarray <illegal type>
    //   114: dup
    //   115: iconst_0
    //   116: sipush 383
    //   119: iastore
    //   120: ldc 45
    //   122: invokespecial 37	com/google/zxing/oned/EANManufacturerOrgSupport:add	([ILjava/lang/String;)V
    //   125: aload_0
    //   126: iconst_1
    //   127: newarray <illegal type>
    //   129: dup
    //   130: iconst_0
    //   131: sipush 385
    //   134: iastore
    //   135: ldc 47
    //   137: invokespecial 37	com/google/zxing/oned/EANManufacturerOrgSupport:add	([ILjava/lang/String;)V
    //   140: aload_0
    //   141: iconst_1
    //   142: newarray <illegal type>
    //   144: dup
    //   145: iconst_0
    //   146: sipush 387
    //   149: iastore
    //   150: ldc 49
    //   152: invokespecial 37	com/google/zxing/oned/EANManufacturerOrgSupport:add	([ILjava/lang/String;)V
    //   155: aload_0
    //   156: iconst_2
    //   157: newarray <illegal type>
    //   159: dup
    //   160: iconst_0
    //   161: sipush 400
    //   164: iastore
    //   165: dup
    //   166: iconst_1
    //   167: sipush 440
    //   170: iastore
    //   171: ldc 51
    //   173: invokespecial 37	com/google/zxing/oned/EANManufacturerOrgSupport:add	([ILjava/lang/String;)V
    //   176: aload_0
    //   177: iconst_2
    //   178: newarray <illegal type>
    //   180: dup
    //   181: iconst_0
    //   182: sipush 450
    //   185: iastore
    //   186: dup
    //   187: iconst_1
    //   188: sipush 459
    //   191: iastore
    //   192: ldc 53
    //   194: invokespecial 37	com/google/zxing/oned/EANManufacturerOrgSupport:add	([ILjava/lang/String;)V
    //   197: aload_0
    //   198: iconst_2
    //   199: newarray <illegal type>
    //   201: dup
    //   202: iconst_0
    //   203: sipush 460
    //   206: iastore
    //   207: dup
    //   208: iconst_1
    //   209: sipush 469
    //   212: iastore
    //   213: ldc 55
    //   215: invokespecial 37	com/google/zxing/oned/EANManufacturerOrgSupport:add	([ILjava/lang/String;)V
    //   218: aload_0
    //   219: iconst_1
    //   220: newarray <illegal type>
    //   222: dup
    //   223: iconst_0
    //   224: sipush 471
    //   227: iastore
    //   228: ldc 57
    //   230: invokespecial 37	com/google/zxing/oned/EANManufacturerOrgSupport:add	([ILjava/lang/String;)V
    //   233: aload_0
    //   234: iconst_1
    //   235: newarray <illegal type>
    //   237: dup
    //   238: iconst_0
    //   239: sipush 474
    //   242: iastore
    //   243: ldc 59
    //   245: invokespecial 37	com/google/zxing/oned/EANManufacturerOrgSupport:add	([ILjava/lang/String;)V
    //   248: aload_0
    //   249: iconst_1
    //   250: newarray <illegal type>
    //   252: dup
    //   253: iconst_0
    //   254: sipush 475
    //   257: iastore
    //   258: ldc 61
    //   260: invokespecial 37	com/google/zxing/oned/EANManufacturerOrgSupport:add	([ILjava/lang/String;)V
    //   263: aload_0
    //   264: iconst_1
    //   265: newarray <illegal type>
    //   267: dup
    //   268: iconst_0
    //   269: sipush 476
    //   272: iastore
    //   273: ldc 63
    //   275: invokespecial 37	com/google/zxing/oned/EANManufacturerOrgSupport:add	([ILjava/lang/String;)V
    //   278: aload_0
    //   279: iconst_1
    //   280: newarray <illegal type>
    //   282: dup
    //   283: iconst_0
    //   284: sipush 477
    //   287: iastore
    //   288: ldc 65
    //   290: invokespecial 37	com/google/zxing/oned/EANManufacturerOrgSupport:add	([ILjava/lang/String;)V
    //   293: aload_0
    //   294: iconst_1
    //   295: newarray <illegal type>
    //   297: dup
    //   298: iconst_0
    //   299: sipush 478
    //   302: iastore
    //   303: ldc 67
    //   305: invokespecial 37	com/google/zxing/oned/EANManufacturerOrgSupport:add	([ILjava/lang/String;)V
    //   308: aload_0
    //   309: iconst_1
    //   310: newarray <illegal type>
    //   312: dup
    //   313: iconst_0
    //   314: sipush 479
    //   317: iastore
    //   318: ldc 69
    //   320: invokespecial 37	com/google/zxing/oned/EANManufacturerOrgSupport:add	([ILjava/lang/String;)V
    //   323: aload_0
    //   324: iconst_1
    //   325: newarray <illegal type>
    //   327: dup
    //   328: iconst_0
    //   329: sipush 480
    //   332: iastore
    //   333: ldc 71
    //   335: invokespecial 37	com/google/zxing/oned/EANManufacturerOrgSupport:add	([ILjava/lang/String;)V
    //   338: aload_0
    //   339: iconst_1
    //   340: newarray <illegal type>
    //   342: dup
    //   343: iconst_0
    //   344: sipush 481
    //   347: iastore
    //   348: ldc 73
    //   350: invokespecial 37	com/google/zxing/oned/EANManufacturerOrgSupport:add	([ILjava/lang/String;)V
    //   353: aload_0
    //   354: iconst_1
    //   355: newarray <illegal type>
    //   357: dup
    //   358: iconst_0
    //   359: sipush 482
    //   362: iastore
    //   363: ldc 75
    //   365: invokespecial 37	com/google/zxing/oned/EANManufacturerOrgSupport:add	([ILjava/lang/String;)V
    //   368: aload_0
    //   369: iconst_1
    //   370: newarray <illegal type>
    //   372: dup
    //   373: iconst_0
    //   374: sipush 484
    //   377: iastore
    //   378: ldc 77
    //   380: invokespecial 37	com/google/zxing/oned/EANManufacturerOrgSupport:add	([ILjava/lang/String;)V
    //   383: aload_0
    //   384: iconst_1
    //   385: newarray <illegal type>
    //   387: dup
    //   388: iconst_0
    //   389: sipush 485
    //   392: iastore
    //   393: ldc 79
    //   395: invokespecial 37	com/google/zxing/oned/EANManufacturerOrgSupport:add	([ILjava/lang/String;)V
    //   398: aload_0
    //   399: iconst_1
    //   400: newarray <illegal type>
    //   402: dup
    //   403: iconst_0
    //   404: sipush 486
    //   407: iastore
    //   408: ldc 81
    //   410: invokespecial 37	com/google/zxing/oned/EANManufacturerOrgSupport:add	([ILjava/lang/String;)V
    //   413: aload_0
    //   414: iconst_1
    //   415: newarray <illegal type>
    //   417: dup
    //   418: iconst_0
    //   419: sipush 487
    //   422: iastore
    //   423: ldc 83
    //   425: invokespecial 37	com/google/zxing/oned/EANManufacturerOrgSupport:add	([ILjava/lang/String;)V
    //   428: aload_0
    //   429: iconst_1
    //   430: newarray <illegal type>
    //   432: dup
    //   433: iconst_0
    //   434: sipush 489
    //   437: iastore
    //   438: ldc 85
    //   440: invokespecial 37	com/google/zxing/oned/EANManufacturerOrgSupport:add	([ILjava/lang/String;)V
    //   443: aload_0
    //   444: iconst_2
    //   445: newarray <illegal type>
    //   447: dup
    //   448: iconst_0
    //   449: sipush 490
    //   452: iastore
    //   453: dup
    //   454: iconst_1
    //   455: sipush 499
    //   458: iastore
    //   459: ldc 53
    //   461: invokespecial 37	com/google/zxing/oned/EANManufacturerOrgSupport:add	([ILjava/lang/String;)V
    //   464: aload_0
    //   465: iconst_2
    //   466: newarray <illegal type>
    //   468: dup
    //   469: iconst_0
    //   470: sipush 500
    //   473: iastore
    //   474: dup
    //   475: iconst_1
    //   476: sipush 509
    //   479: iastore
    //   480: ldc 87
    //   482: invokespecial 37	com/google/zxing/oned/EANManufacturerOrgSupport:add	([ILjava/lang/String;)V
    //   485: aload_0
    //   486: iconst_1
    //   487: newarray <illegal type>
    //   489: dup
    //   490: iconst_0
    //   491: sipush 520
    //   494: iastore
    //   495: ldc 89
    //   497: invokespecial 37	com/google/zxing/oned/EANManufacturerOrgSupport:add	([ILjava/lang/String;)V
    //   500: aload_0
    //   501: iconst_1
    //   502: newarray <illegal type>
    //   504: dup
    //   505: iconst_0
    //   506: sipush 528
    //   509: iastore
    //   510: ldc 91
    //   512: invokespecial 37	com/google/zxing/oned/EANManufacturerOrgSupport:add	([ILjava/lang/String;)V
    //   515: aload_0
    //   516: iconst_1
    //   517: newarray <illegal type>
    //   519: dup
    //   520: iconst_0
    //   521: sipush 529
    //   524: iastore
    //   525: ldc 93
    //   527: invokespecial 37	com/google/zxing/oned/EANManufacturerOrgSupport:add	([ILjava/lang/String;)V
    //   530: aload_0
    //   531: iconst_1
    //   532: newarray <illegal type>
    //   534: dup
    //   535: iconst_0
    //   536: sipush 531
    //   539: iastore
    //   540: ldc 95
    //   542: invokespecial 37	com/google/zxing/oned/EANManufacturerOrgSupport:add	([ILjava/lang/String;)V
    //   545: aload_0
    //   546: iconst_1
    //   547: newarray <illegal type>
    //   549: dup
    //   550: iconst_0
    //   551: sipush 535
    //   554: iastore
    //   555: ldc 97
    //   557: invokespecial 37	com/google/zxing/oned/EANManufacturerOrgSupport:add	([ILjava/lang/String;)V
    //   560: aload_0
    //   561: iconst_1
    //   562: newarray <illegal type>
    //   564: dup
    //   565: iconst_0
    //   566: sipush 539
    //   569: iastore
    //   570: ldc 99
    //   572: invokespecial 37	com/google/zxing/oned/EANManufacturerOrgSupport:add	([ILjava/lang/String;)V
    //   575: aload_0
    //   576: iconst_2
    //   577: newarray <illegal type>
    //   579: dup
    //   580: iconst_0
    //   581: sipush 540
    //   584: iastore
    //   585: dup
    //   586: iconst_1
    //   587: sipush 549
    //   590: iastore
    //   591: ldc 101
    //   593: invokespecial 37	com/google/zxing/oned/EANManufacturerOrgSupport:add	([ILjava/lang/String;)V
    //   596: aload_0
    //   597: iconst_1
    //   598: newarray <illegal type>
    //   600: dup
    //   601: iconst_0
    //   602: sipush 560
    //   605: iastore
    //   606: ldc 103
    //   608: invokespecial 37	com/google/zxing/oned/EANManufacturerOrgSupport:add	([ILjava/lang/String;)V
    //   611: aload_0
    //   612: iconst_1
    //   613: newarray <illegal type>
    //   615: dup
    //   616: iconst_0
    //   617: sipush 569
    //   620: iastore
    //   621: ldc 105
    //   623: invokespecial 37	com/google/zxing/oned/EANManufacturerOrgSupport:add	([ILjava/lang/String;)V
    //   626: aload_0
    //   627: iconst_2
    //   628: newarray <illegal type>
    //   630: dup
    //   631: iconst_0
    //   632: sipush 570
    //   635: iastore
    //   636: dup
    //   637: iconst_1
    //   638: sipush 579
    //   641: iastore
    //   642: ldc 107
    //   644: invokespecial 37	com/google/zxing/oned/EANManufacturerOrgSupport:add	([ILjava/lang/String;)V
    //   647: aload_0
    //   648: iconst_1
    //   649: newarray <illegal type>
    //   651: dup
    //   652: iconst_0
    //   653: sipush 590
    //   656: iastore
    //   657: ldc 109
    //   659: invokespecial 37	com/google/zxing/oned/EANManufacturerOrgSupport:add	([ILjava/lang/String;)V
    //   662: aload_0
    //   663: iconst_1
    //   664: newarray <illegal type>
    //   666: dup
    //   667: iconst_0
    //   668: sipush 594
    //   671: iastore
    //   672: ldc 111
    //   674: invokespecial 37	com/google/zxing/oned/EANManufacturerOrgSupport:add	([ILjava/lang/String;)V
    //   677: aload_0
    //   678: iconst_1
    //   679: newarray <illegal type>
    //   681: dup
    //   682: iconst_0
    //   683: sipush 599
    //   686: iastore
    //   687: ldc 113
    //   689: invokespecial 37	com/google/zxing/oned/EANManufacturerOrgSupport:add	([ILjava/lang/String;)V
    //   692: aload_0
    //   693: iconst_2
    //   694: newarray <illegal type>
    //   696: dup
    //   697: iconst_0
    //   698: sipush 600
    //   701: iastore
    //   702: dup
    //   703: iconst_1
    //   704: sipush 601
    //   707: iastore
    //   708: ldc 115
    //   710: invokespecial 37	com/google/zxing/oned/EANManufacturerOrgSupport:add	([ILjava/lang/String;)V
    //   713: aload_0
    //   714: iconst_1
    //   715: newarray <illegal type>
    //   717: dup
    //   718: iconst_0
    //   719: sipush 603
    //   722: iastore
    //   723: ldc 117
    //   725: invokespecial 37	com/google/zxing/oned/EANManufacturerOrgSupport:add	([ILjava/lang/String;)V
    //   728: aload_0
    //   729: iconst_1
    //   730: newarray <illegal type>
    //   732: dup
    //   733: iconst_0
    //   734: sipush 608
    //   737: iastore
    //   738: ldc 119
    //   740: invokespecial 37	com/google/zxing/oned/EANManufacturerOrgSupport:add	([ILjava/lang/String;)V
    //   743: aload_0
    //   744: iconst_1
    //   745: newarray <illegal type>
    //   747: dup
    //   748: iconst_0
    //   749: sipush 609
    //   752: iastore
    //   753: ldc 121
    //   755: invokespecial 37	com/google/zxing/oned/EANManufacturerOrgSupport:add	([ILjava/lang/String;)V
    //   758: aload_0
    //   759: iconst_1
    //   760: newarray <illegal type>
    //   762: dup
    //   763: iconst_0
    //   764: sipush 611
    //   767: iastore
    //   768: ldc 123
    //   770: invokespecial 37	com/google/zxing/oned/EANManufacturerOrgSupport:add	([ILjava/lang/String;)V
    //   773: aload_0
    //   774: iconst_1
    //   775: newarray <illegal type>
    //   777: dup
    //   778: iconst_0
    //   779: sipush 613
    //   782: iastore
    //   783: ldc 125
    //   785: invokespecial 37	com/google/zxing/oned/EANManufacturerOrgSupport:add	([ILjava/lang/String;)V
    //   788: aload_0
    //   789: iconst_1
    //   790: newarray <illegal type>
    //   792: dup
    //   793: iconst_0
    //   794: sipush 616
    //   797: iastore
    //   798: ldc 127
    //   800: invokespecial 37	com/google/zxing/oned/EANManufacturerOrgSupport:add	([ILjava/lang/String;)V
    //   803: aload_0
    //   804: iconst_1
    //   805: newarray <illegal type>
    //   807: dup
    //   808: iconst_0
    //   809: sipush 618
    //   812: iastore
    //   813: ldc -127
    //   815: invokespecial 37	com/google/zxing/oned/EANManufacturerOrgSupport:add	([ILjava/lang/String;)V
    //   818: aload_0
    //   819: iconst_1
    //   820: newarray <illegal type>
    //   822: dup
    //   823: iconst_0
    //   824: sipush 619
    //   827: iastore
    //   828: ldc -125
    //   830: invokespecial 37	com/google/zxing/oned/EANManufacturerOrgSupport:add	([ILjava/lang/String;)V
    //   833: aload_0
    //   834: iconst_1
    //   835: newarray <illegal type>
    //   837: dup
    //   838: iconst_0
    //   839: sipush 621
    //   842: iastore
    //   843: ldc -123
    //   845: invokespecial 37	com/google/zxing/oned/EANManufacturerOrgSupport:add	([ILjava/lang/String;)V
    //   848: aload_0
    //   849: iconst_1
    //   850: newarray <illegal type>
    //   852: dup
    //   853: iconst_0
    //   854: sipush 622
    //   857: iastore
    //   858: ldc -121
    //   860: invokespecial 37	com/google/zxing/oned/EANManufacturerOrgSupport:add	([ILjava/lang/String;)V
    //   863: aload_0
    //   864: iconst_1
    //   865: newarray <illegal type>
    //   867: dup
    //   868: iconst_0
    //   869: sipush 624
    //   872: iastore
    //   873: ldc -119
    //   875: invokespecial 37	com/google/zxing/oned/EANManufacturerOrgSupport:add	([ILjava/lang/String;)V
    //   878: aload_0
    //   879: iconst_1
    //   880: newarray <illegal type>
    //   882: dup
    //   883: iconst_0
    //   884: sipush 625
    //   887: iastore
    //   888: ldc -117
    //   890: invokespecial 37	com/google/zxing/oned/EANManufacturerOrgSupport:add	([ILjava/lang/String;)V
    //   893: aload_0
    //   894: iconst_1
    //   895: newarray <illegal type>
    //   897: dup
    //   898: iconst_0
    //   899: sipush 626
    //   902: iastore
    //   903: ldc -115
    //   905: invokespecial 37	com/google/zxing/oned/EANManufacturerOrgSupport:add	([ILjava/lang/String;)V
    //   908: aload_0
    //   909: iconst_1
    //   910: newarray <illegal type>
    //   912: dup
    //   913: iconst_0
    //   914: sipush 627
    //   917: iastore
    //   918: ldc -113
    //   920: invokespecial 37	com/google/zxing/oned/EANManufacturerOrgSupport:add	([ILjava/lang/String;)V
    //   923: aload_0
    //   924: iconst_1
    //   925: newarray <illegal type>
    //   927: dup
    //   928: iconst_0
    //   929: sipush 628
    //   932: iastore
    //   933: ldc -111
    //   935: invokespecial 37	com/google/zxing/oned/EANManufacturerOrgSupport:add	([ILjava/lang/String;)V
    //   938: aload_0
    //   939: iconst_1
    //   940: newarray <illegal type>
    //   942: dup
    //   943: iconst_0
    //   944: sipush 629
    //   947: iastore
    //   948: ldc -109
    //   950: invokespecial 37	com/google/zxing/oned/EANManufacturerOrgSupport:add	([ILjava/lang/String;)V
    //   953: aload_0
    //   954: iconst_2
    //   955: newarray <illegal type>
    //   957: dup
    //   958: iconst_0
    //   959: sipush 640
    //   962: iastore
    //   963: dup
    //   964: iconst_1
    //   965: sipush 649
    //   968: iastore
    //   969: ldc -107
    //   971: invokespecial 37	com/google/zxing/oned/EANManufacturerOrgSupport:add	([ILjava/lang/String;)V
    //   974: aload_0
    //   975: iconst_2
    //   976: newarray <illegal type>
    //   978: dup
    //   979: iconst_0
    //   980: sipush 690
    //   983: iastore
    //   984: dup
    //   985: iconst_1
    //   986: sipush 695
    //   989: iastore
    //   990: ldc -105
    //   992: invokespecial 37	com/google/zxing/oned/EANManufacturerOrgSupport:add	([ILjava/lang/String;)V
    //   995: aload_0
    //   996: iconst_2
    //   997: newarray <illegal type>
    //   999: dup
    //   1000: iconst_0
    //   1001: sipush 700
    //   1004: iastore
    //   1005: dup
    //   1006: iconst_1
    //   1007: sipush 709
    //   1010: iastore
    //   1011: ldc -103
    //   1013: invokespecial 37	com/google/zxing/oned/EANManufacturerOrgSupport:add	([ILjava/lang/String;)V
    //   1016: aload_0
    //   1017: iconst_1
    //   1018: newarray <illegal type>
    //   1020: dup
    //   1021: iconst_0
    //   1022: sipush 729
    //   1025: iastore
    //   1026: ldc -101
    //   1028: invokespecial 37	com/google/zxing/oned/EANManufacturerOrgSupport:add	([ILjava/lang/String;)V
    //   1031: aload_0
    //   1032: iconst_2
    //   1033: newarray <illegal type>
    //   1035: dup
    //   1036: iconst_0
    //   1037: sipush 730
    //   1040: iastore
    //   1041: dup
    //   1042: iconst_1
    //   1043: sipush 739
    //   1046: iastore
    //   1047: ldc -99
    //   1049: invokespecial 37	com/google/zxing/oned/EANManufacturerOrgSupport:add	([ILjava/lang/String;)V
    //   1052: aload_0
    //   1053: iconst_1
    //   1054: newarray <illegal type>
    //   1056: dup
    //   1057: iconst_0
    //   1058: sipush 740
    //   1061: iastore
    //   1062: ldc -97
    //   1064: invokespecial 37	com/google/zxing/oned/EANManufacturerOrgSupport:add	([ILjava/lang/String;)V
    //   1067: aload_0
    //   1068: iconst_1
    //   1069: newarray <illegal type>
    //   1071: dup
    //   1072: iconst_0
    //   1073: sipush 741
    //   1076: iastore
    //   1077: ldc -95
    //   1079: invokespecial 37	com/google/zxing/oned/EANManufacturerOrgSupport:add	([ILjava/lang/String;)V
    //   1082: aload_0
    //   1083: iconst_1
    //   1084: newarray <illegal type>
    //   1086: dup
    //   1087: iconst_0
    //   1088: sipush 742
    //   1091: iastore
    //   1092: ldc -93
    //   1094: invokespecial 37	com/google/zxing/oned/EANManufacturerOrgSupport:add	([ILjava/lang/String;)V
    //   1097: aload_0
    //   1098: iconst_1
    //   1099: newarray <illegal type>
    //   1101: dup
    //   1102: iconst_0
    //   1103: sipush 743
    //   1106: iastore
    //   1107: ldc -91
    //   1109: invokespecial 37	com/google/zxing/oned/EANManufacturerOrgSupport:add	([ILjava/lang/String;)V
    //   1112: aload_0
    //   1113: iconst_1
    //   1114: newarray <illegal type>
    //   1116: dup
    //   1117: iconst_0
    //   1118: sipush 744
    //   1121: iastore
    //   1122: ldc -89
    //   1124: invokespecial 37	com/google/zxing/oned/EANManufacturerOrgSupport:add	([ILjava/lang/String;)V
    //   1127: aload_0
    //   1128: iconst_1
    //   1129: newarray <illegal type>
    //   1131: dup
    //   1132: iconst_0
    //   1133: sipush 745
    //   1136: iastore
    //   1137: ldc -87
    //   1139: invokespecial 37	com/google/zxing/oned/EANManufacturerOrgSupport:add	([ILjava/lang/String;)V
    //   1142: aload_0
    //   1143: iconst_1
    //   1144: newarray <illegal type>
    //   1146: dup
    //   1147: iconst_0
    //   1148: sipush 746
    //   1151: iastore
    //   1152: ldc -85
    //   1154: invokespecial 37	com/google/zxing/oned/EANManufacturerOrgSupport:add	([ILjava/lang/String;)V
    //   1157: aload_0
    //   1158: iconst_1
    //   1159: newarray <illegal type>
    //   1161: dup
    //   1162: iconst_0
    //   1163: sipush 750
    //   1166: iastore
    //   1167: ldc -83
    //   1169: invokespecial 37	com/google/zxing/oned/EANManufacturerOrgSupport:add	([ILjava/lang/String;)V
    //   1172: aload_0
    //   1173: iconst_2
    //   1174: newarray <illegal type>
    //   1176: dup
    //   1177: iconst_0
    //   1178: sipush 754
    //   1181: iastore
    //   1182: dup
    //   1183: iconst_1
    //   1184: sipush 755
    //   1187: iastore
    //   1188: ldc -81
    //   1190: invokespecial 37	com/google/zxing/oned/EANManufacturerOrgSupport:add	([ILjava/lang/String;)V
    //   1193: aload_0
    //   1194: iconst_1
    //   1195: newarray <illegal type>
    //   1197: dup
    //   1198: iconst_0
    //   1199: sipush 759
    //   1202: iastore
    //   1203: ldc -79
    //   1205: invokespecial 37	com/google/zxing/oned/EANManufacturerOrgSupport:add	([ILjava/lang/String;)V
    //   1208: aload_0
    //   1209: iconst_2
    //   1210: newarray <illegal type>
    //   1212: dup
    //   1213: iconst_0
    //   1214: sipush 760
    //   1217: iastore
    //   1218: dup
    //   1219: iconst_1
    //   1220: sipush 769
    //   1223: iastore
    //   1224: ldc -77
    //   1226: invokespecial 37	com/google/zxing/oned/EANManufacturerOrgSupport:add	([ILjava/lang/String;)V
    //   1229: aload_0
    //   1230: iconst_1
    //   1231: newarray <illegal type>
    //   1233: dup
    //   1234: iconst_0
    //   1235: sipush 770
    //   1238: iastore
    //   1239: ldc -75
    //   1241: invokespecial 37	com/google/zxing/oned/EANManufacturerOrgSupport:add	([ILjava/lang/String;)V
    //   1244: aload_0
    //   1245: iconst_1
    //   1246: newarray <illegal type>
    //   1248: dup
    //   1249: iconst_0
    //   1250: sipush 773
    //   1253: iastore
    //   1254: ldc -73
    //   1256: invokespecial 37	com/google/zxing/oned/EANManufacturerOrgSupport:add	([ILjava/lang/String;)V
    //   1259: aload_0
    //   1260: iconst_1
    //   1261: newarray <illegal type>
    //   1263: dup
    //   1264: iconst_0
    //   1265: sipush 775
    //   1268: iastore
    //   1269: ldc -71
    //   1271: invokespecial 37	com/google/zxing/oned/EANManufacturerOrgSupport:add	([ILjava/lang/String;)V
    //   1274: aload_0
    //   1275: iconst_1
    //   1276: newarray <illegal type>
    //   1278: dup
    //   1279: iconst_0
    //   1280: sipush 777
    //   1283: iastore
    //   1284: ldc -69
    //   1286: invokespecial 37	com/google/zxing/oned/EANManufacturerOrgSupport:add	([ILjava/lang/String;)V
    //   1289: aload_0
    //   1290: iconst_1
    //   1291: newarray <illegal type>
    //   1293: dup
    //   1294: iconst_0
    //   1295: sipush 779
    //   1298: iastore
    //   1299: ldc -67
    //   1301: invokespecial 37	com/google/zxing/oned/EANManufacturerOrgSupport:add	([ILjava/lang/String;)V
    //   1304: aload_0
    //   1305: iconst_1
    //   1306: newarray <illegal type>
    //   1308: dup
    //   1309: iconst_0
    //   1310: sipush 780
    //   1313: iastore
    //   1314: ldc -65
    //   1316: invokespecial 37	com/google/zxing/oned/EANManufacturerOrgSupport:add	([ILjava/lang/String;)V
    //   1319: aload_0
    //   1320: iconst_1
    //   1321: newarray <illegal type>
    //   1323: dup
    //   1324: iconst_0
    //   1325: sipush 784
    //   1328: iastore
    //   1329: ldc -63
    //   1331: invokespecial 37	com/google/zxing/oned/EANManufacturerOrgSupport:add	([ILjava/lang/String;)V
    //   1334: aload_0
    //   1335: iconst_1
    //   1336: newarray <illegal type>
    //   1338: dup
    //   1339: iconst_0
    //   1340: sipush 785
    //   1343: iastore
    //   1344: ldc -71
    //   1346: invokespecial 37	com/google/zxing/oned/EANManufacturerOrgSupport:add	([ILjava/lang/String;)V
    //   1349: aload_0
    //   1350: iconst_1
    //   1351: newarray <illegal type>
    //   1353: dup
    //   1354: iconst_0
    //   1355: sipush 786
    //   1358: iastore
    //   1359: ldc -61
    //   1361: invokespecial 37	com/google/zxing/oned/EANManufacturerOrgSupport:add	([ILjava/lang/String;)V
    //   1364: aload_0
    //   1365: iconst_2
    //   1366: newarray <illegal type>
    //   1368: dup
    //   1369: iconst_0
    //   1370: sipush 789
    //   1373: iastore
    //   1374: dup
    //   1375: iconst_1
    //   1376: sipush 790
    //   1379: iastore
    //   1380: ldc -59
    //   1382: invokespecial 37	com/google/zxing/oned/EANManufacturerOrgSupport:add	([ILjava/lang/String;)V
    //   1385: aload_0
    //   1386: iconst_2
    //   1387: newarray <illegal type>
    //   1389: dup
    //   1390: iconst_0
    //   1391: sipush 800
    //   1394: iastore
    //   1395: dup
    //   1396: iconst_1
    //   1397: sipush 839
    //   1400: iastore
    //   1401: ldc -57
    //   1403: invokespecial 37	com/google/zxing/oned/EANManufacturerOrgSupport:add	([ILjava/lang/String;)V
    //   1406: aload_0
    //   1407: iconst_2
    //   1408: newarray <illegal type>
    //   1410: dup
    //   1411: iconst_0
    //   1412: sipush 840
    //   1415: iastore
    //   1416: dup
    //   1417: iconst_1
    //   1418: sipush 849
    //   1421: iastore
    //   1422: ldc -55
    //   1424: invokespecial 37	com/google/zxing/oned/EANManufacturerOrgSupport:add	([ILjava/lang/String;)V
    //   1427: aload_0
    //   1428: iconst_1
    //   1429: newarray <illegal type>
    //   1431: dup
    //   1432: iconst_0
    //   1433: sipush 850
    //   1436: iastore
    //   1437: ldc -53
    //   1439: invokespecial 37	com/google/zxing/oned/EANManufacturerOrgSupport:add	([ILjava/lang/String;)V
    //   1442: aload_0
    //   1443: iconst_1
    //   1444: newarray <illegal type>
    //   1446: dup
    //   1447: iconst_0
    //   1448: sipush 858
    //   1451: iastore
    //   1452: ldc -51
    //   1454: invokespecial 37	com/google/zxing/oned/EANManufacturerOrgSupport:add	([ILjava/lang/String;)V
    //   1457: aload_0
    //   1458: iconst_1
    //   1459: newarray <illegal type>
    //   1461: dup
    //   1462: iconst_0
    //   1463: sipush 859
    //   1466: iastore
    //   1467: ldc -49
    //   1469: invokespecial 37	com/google/zxing/oned/EANManufacturerOrgSupport:add	([ILjava/lang/String;)V
    //   1472: aload_0
    //   1473: iconst_1
    //   1474: newarray <illegal type>
    //   1476: dup
    //   1477: iconst_0
    //   1478: sipush 860
    //   1481: iastore
    //   1482: ldc -47
    //   1484: invokespecial 37	com/google/zxing/oned/EANManufacturerOrgSupport:add	([ILjava/lang/String;)V
    //   1487: aload_0
    //   1488: iconst_1
    //   1489: newarray <illegal type>
    //   1491: dup
    //   1492: iconst_0
    //   1493: sipush 865
    //   1496: iastore
    //   1497: ldc -45
    //   1499: invokespecial 37	com/google/zxing/oned/EANManufacturerOrgSupport:add	([ILjava/lang/String;)V
    //   1502: aload_0
    //   1503: iconst_1
    //   1504: newarray <illegal type>
    //   1506: dup
    //   1507: iconst_0
    //   1508: sipush 867
    //   1511: iastore
    //   1512: ldc -43
    //   1514: invokespecial 37	com/google/zxing/oned/EANManufacturerOrgSupport:add	([ILjava/lang/String;)V
    //   1517: aload_0
    //   1518: iconst_2
    //   1519: newarray <illegal type>
    //   1521: dup
    //   1522: iconst_0
    //   1523: sipush 868
    //   1526: iastore
    //   1527: dup
    //   1528: iconst_1
    //   1529: sipush 869
    //   1532: iastore
    //   1533: ldc -41
    //   1535: invokespecial 37	com/google/zxing/oned/EANManufacturerOrgSupport:add	([ILjava/lang/String;)V
    //   1538: aload_0
    //   1539: iconst_2
    //   1540: newarray <illegal type>
    //   1542: dup
    //   1543: iconst_0
    //   1544: sipush 870
    //   1547: iastore
    //   1548: dup
    //   1549: iconst_1
    //   1550: sipush 879
    //   1553: iastore
    //   1554: ldc -39
    //   1556: invokespecial 37	com/google/zxing/oned/EANManufacturerOrgSupport:add	([ILjava/lang/String;)V
    //   1559: aload_0
    //   1560: iconst_1
    //   1561: newarray <illegal type>
    //   1563: dup
    //   1564: iconst_0
    //   1565: sipush 880
    //   1568: iastore
    //   1569: ldc -37
    //   1571: invokespecial 37	com/google/zxing/oned/EANManufacturerOrgSupport:add	([ILjava/lang/String;)V
    //   1574: aload_0
    //   1575: iconst_1
    //   1576: newarray <illegal type>
    //   1578: dup
    //   1579: iconst_0
    //   1580: sipush 885
    //   1583: iastore
    //   1584: ldc -35
    //   1586: invokespecial 37	com/google/zxing/oned/EANManufacturerOrgSupport:add	([ILjava/lang/String;)V
    //   1589: aload_0
    //   1590: iconst_1
    //   1591: newarray <illegal type>
    //   1593: dup
    //   1594: iconst_0
    //   1595: sipush 888
    //   1598: iastore
    //   1599: ldc -33
    //   1601: invokespecial 37	com/google/zxing/oned/EANManufacturerOrgSupport:add	([ILjava/lang/String;)V
    //   1604: aload_0
    //   1605: iconst_1
    //   1606: newarray <illegal type>
    //   1608: dup
    //   1609: iconst_0
    //   1610: sipush 890
    //   1613: iastore
    //   1614: ldc -31
    //   1616: invokespecial 37	com/google/zxing/oned/EANManufacturerOrgSupport:add	([ILjava/lang/String;)V
    //   1619: aload_0
    //   1620: iconst_1
    //   1621: newarray <illegal type>
    //   1623: dup
    //   1624: iconst_0
    //   1625: sipush 893
    //   1628: iastore
    //   1629: ldc -29
    //   1631: invokespecial 37	com/google/zxing/oned/EANManufacturerOrgSupport:add	([ILjava/lang/String;)V
    //   1634: aload_0
    //   1635: iconst_1
    //   1636: newarray <illegal type>
    //   1638: dup
    //   1639: iconst_0
    //   1640: sipush 896
    //   1643: iastore
    //   1644: ldc -27
    //   1646: invokespecial 37	com/google/zxing/oned/EANManufacturerOrgSupport:add	([ILjava/lang/String;)V
    //   1649: aload_0
    //   1650: iconst_1
    //   1651: newarray <illegal type>
    //   1653: dup
    //   1654: iconst_0
    //   1655: sipush 899
    //   1658: iastore
    //   1659: ldc -25
    //   1661: invokespecial 37	com/google/zxing/oned/EANManufacturerOrgSupport:add	([ILjava/lang/String;)V
    //   1664: aload_0
    //   1665: iconst_2
    //   1666: newarray <illegal type>
    //   1668: dup
    //   1669: iconst_0
    //   1670: sipush 900
    //   1673: iastore
    //   1674: dup
    //   1675: iconst_1
    //   1676: sipush 919
    //   1679: iastore
    //   1680: ldc -23
    //   1682: invokespecial 37	com/google/zxing/oned/EANManufacturerOrgSupport:add	([ILjava/lang/String;)V
    //   1685: aload_0
    //   1686: iconst_2
    //   1687: newarray <illegal type>
    //   1689: dup
    //   1690: iconst_0
    //   1691: sipush 930
    //   1694: iastore
    //   1695: dup
    //   1696: iconst_1
    //   1697: sipush 939
    //   1700: iastore
    //   1701: ldc -21
    //   1703: invokespecial 37	com/google/zxing/oned/EANManufacturerOrgSupport:add	([ILjava/lang/String;)V
    //   1706: aload_0
    //   1707: iconst_2
    //   1708: newarray <illegal type>
    //   1710: dup
    //   1711: iconst_0
    //   1712: sipush 940
    //   1715: iastore
    //   1716: dup
    //   1717: iconst_1
    //   1718: sipush 949
    //   1721: iastore
    //   1722: ldc 63
    //   1724: invokespecial 37	com/google/zxing/oned/EANManufacturerOrgSupport:add	([ILjava/lang/String;)V
    //   1727: aload_0
    //   1728: iconst_1
    //   1729: newarray <illegal type>
    //   1731: dup
    //   1732: iconst_0
    //   1733: sipush 955
    //   1736: iastore
    //   1737: ldc -19
    //   1739: invokespecial 37	com/google/zxing/oned/EANManufacturerOrgSupport:add	([ILjava/lang/String;)V
    //   1742: aload_0
    //   1743: iconst_1
    //   1744: newarray <illegal type>
    //   1746: dup
    //   1747: iconst_0
    //   1748: sipush 958
    //   1751: iastore
    //   1752: ldc -17
    //   1754: invokespecial 37	com/google/zxing/oned/EANManufacturerOrgSupport:add	([ILjava/lang/String;)V
    //   1757: goto -1741 -> 16
    //   1760: astore_2
    //   1761: aload_0
    //   1762: monitorexit
    //   1763: aload_2
    //   1764: athrow
    // Local variable table:
    //   start	length	slot	name	signature
    //   0	1765	0	this	EANManufacturerOrgSupport
    //   11	2	1	bool	boolean
    //   22	8	2	arrayOfInt	int[]
    //   1760	4	2	localObject	Object
    // Exception table:
    //   from	to	target	type
    //   2	12	1760	finally
    //   19	23	1760	finally
    //   28	1757	1760	finally
  }
  
  String lookupCountryIdentifier(String paramString)
  {
    initIfNeeded();
    int k = Integer.parseInt(paramString.substring(0, 3));
    int m = this.ranges.size();
    int i = 0;
    for (;;)
    {
      if (i >= m) {}
      int j;
      do
      {
        return null;
        paramString = (int[])this.ranges.get(i);
        j = paramString[0];
      } while (k < j);
      if (paramString.length == 1) {}
      while (k <= j)
      {
        return (String)this.countryIdentifiers.get(i);
        j = paramString[1];
      }
      i += 1;
    }
  }
}


/* Location:              C:\Users\ADMIN\Desktop\foss\dex2jar-2.0\classes-dex2jar.jar!\com\google\zxing\oned\EANManufacturerOrgSupport.class
 * Java compiler version: 6 (50.0)
 * JD-Core Version:       0.7.1
 */